{"$defs":{"cp":{"allOf":[{"if":{"properties":{"country":{"const":"AF","type":"string"}}},"then":{"properties":{"zip":{"pattern":"^\\d{4}$","type":"string"}}}},{"if":{"properties":{"country":{"const":"AX","type":"string"}}},"then":{"properties":{"zip":{"pattern":"^\\d{5}$","type":"string"}}}},{"if":{"properties":{"country":{"const":"AL","type":"string"}}},"then":{"properties":{"zip":{"pattern":"^\\d{4}$","type":"string"}}}},{"if":{"properties":{"country":{"const":"DZ","type":"string"}}},"then":{"properties":{"zip":{"pattern":"^\\d{5}$","type":"string"}}}},{"if":{"properties":{"country":{"const":"AD","type":"string"}}},"then":{"properties":{"zip":{"pattern":"^[Aa][Dd]\\d{3}$","type":"string"}}}},{"if":{"properties":{"country":{"const":"AI","type":"string"}}},"then":{"properties":{"zip":{"pattern":"^[Aa][I][-][2][6][4][0]$","type":"string"}}}},{"if":{"properties":{"country":{"const":"AR","type":"string"}}},"then":{"properties":{"zip":{"pattern":"^[A-HJ-NP-Z]\\d{4}([A-Z]{3})?$","type":"string"}}}},{"if":{"properties":{"country":{"const":"AM","type":"string"}}},"then":{"properties":{"zip":{"pattern":"^\\d{4}$","type":"string"}}}},{"if":{"properties":{"country":{"const":"AU","type":"string"}}},"then":{"properties":{"zip":{"pattern":"^\\d{4}$","type":"string"}}}},{"if":{"properties":{"country":{"const":"AT","type":"string"}}},"then":{"properties":{"zip":{"pattern":"^\\d{4}$","type":"string"}}}},{"if":{"properties":{"country":{"const":"AZ","type":"string"}}},"then":{"properties":{"zip":{"pattern":"^[Aa][Zz]\\d{4}$","type":"string"}}}},{"if":{"properties":{"country":{"const":"BH","type":"string"}}},"then":{"properties":{"zip":{"pattern":"^\\d{3,4}$","type":"string"}}}},{"if":{"properties":{"country":{"const":"BD","type":"string"}}},"then":{"properties":{"zip":{"pattern":"^\\d{4}$","type":"string"}}}},{"if":{"properties":{"country":{"const":"BB","type":"string"}}},"then":{"properties":{"zip":{"pattern":"^BB*\\d{5}$","type":"string"}}}},{"if":{"properties":{"country":{"const":"BY","type":"string"}}},"then":{"properties":{"zip":{"pattern":"^\\d{6}$","type":"string"}}}},{"if":{"properties":{"country":{"const":"BE","type":"string"}}},"then":{"properties":{"zip":{"pattern":"^\\d{4}$","type":"string"}}}},{"if":{"properties":{"country":{"const":"BM","type":"string"}}},"then":{"properties":{"zip":{"pattern":"^[A-Za-z]{2} ([A-Za-z]{2}|\\d{2})$","type":"string"}}}},{"if":{"properties":{"country":{"const":"BT","type":"string"}}},"then":{"properties":{"zip":{"pattern":"^\\d{5}$","type":"string"}}}},{"if":{"properties":{"country":{"const":"BO","type":"string"}}},"then":{"properties":{"zip":{"pattern":"^\\d{4}$","type":"string"}}}},{"if":{"properties":{"country":{"const":"BA","type":"string"}}},"then":{"properties":{"zip":{"pattern":"^\\d{5}$","type":"string"}}}},{"if":{"properties":{"country":{"const":"BR","type":"string"}}},"then":{"properties":{"zip":{"pattern":"^\\d{5}-?\\d{3}$","type":"string"}}}},{"if":{"properties":{"country":{"const":"VG","type":"string"}}},"then":{"properties":{"zip":{"pattern":"^[Vv][Gg]\\d{4}$","type":"string"}}}},{"if":{"properties":{"country":{"const":"BN","type":"string"}}},"then":{"properties":{"zip":{"pattern":"^[A-Za-z]{2}\\d{4}$","type":"string"}}}},{"if":{"properties":{"country":{"const":"BG","type":"string"}}},"then":{"properties":{"zip":{"pattern":"^\\d{4}$","type":"string"}}}},{"if":{"properties":{"country":{"const":"KH","type":"string"}}},"then":{"properties":{"zip":{"pattern":"^\\d{5}$","type":"string"}}}},{"if":{"properties":{"country":{"const":"CA","type":"string"}}},"then":{"properties":{"zip":{"pattern":"^[ABCEGHJKLMNPRSTVXYabceghjklmnprstvxy]\\d[ABCEGHJKLMNPRSTVWXYZabceghjklmnprstvwxyz] ?\\d[ABCEGHJKLMNPRSTVWXYZabceghjklmnprstvwxyz]\\d$","type":"string"}}}},{"if":{"properties":{"country":{"const":"CV","type":"string"}}},"then":{"properties":{"zip":{"pattern":"^\\d{4}$","type":"string"}}}},{"if":{"properties":{"country":{"const":"KY","type":"string"}}},"then":{"properties":{"zip":{"pattern":"^[Kk][Yy]\\d[- ]?\\d{4}$","type":"string"}}}},{"if":{"properties":{"country":{"const":"TD","type":"string"}}},"then":{"properties":{"zip":{"pattern":"^\\d{5}$","type":"string"}}}},{"if":{"properties":{"country":{"const":"CL","type":"string"}}},"then":{"properties":{"zip":{"pattern":"^\\d{7}$","type":"string"}}}},{"if":{"properties":{"country":{"const":"CN","type":"string"}}},"then":{"properties":{"zip":{"pattern":"^\\d{6}$","type":"string"}}}},{"if":{"properties":{"country":{"const":"CX","type":"string"}}},"then":{"properties":{"zip":{"pattern":"^\\d{4}$","type":"string"}}}},{"if":{"properties":{"country":{"const":"CC","type":"string"}}},"then":{"properties":{"zip":{"pattern":"^\\d{4}$","type":"string"}}}},{"if":{"properties":{"country":{"const":"CO","type":"string"}}},"then":{"properties":{"zip":{"pattern":"^\\d{6}$","type":"string"}}}},{"if":{"properties":{"country":{"const":"CD","type":"string"}}},"then":{"properties":{"zip":{"pattern":"^[Cc][Dd]$","type":"string"}}}},{"if":{"properties":{"country":{"const":"CR","type":"string"}}},"then":{"properties":{"zip":{"pattern":"^\\d{4,5}$","type":"string"}}}},{"if":{"properties":{"country":{"const":"HR","type":"string"}}},"then":{"properties":{"zip":{"pattern":"^\\d{5}$","type":"string"}}}},{"if":{"properties":{"country":{"const":"CU","type":"string"}}},"then":{"properties":{"zip":{"pattern":"^\\d{5}$","type":"string"}}}},{"if":{"properties":{"country":{"const":"CY","type":"string"}}},"then":{"properties":{"zip":{"pattern":"^\\d{4}$","type":"string"}}}},{"if":{"properties":{"country":{"const":"CZ","type":"string"}}},"then":{"properties":{"zip":{"pattern":"^\\d{3} ?\\d{2}$","type":"string"}}}},{"if":{"properties":{"country":{"const":"DK","type":"string"}}},"then":{"properties":{"zip":{"pattern":"^\\d{4}$","type":"string"}}}},{"if":{"properties":{"country":{"const":"DO","type":"string"}}},"then":{"properties":{"zip":{"pattern":"^\\d{5}$","type":"string"}}}},{"if":{"properties":{"country":{"const":"EC","type":"string"}}},"then":{"properties":{"zip":{"pattern":"^\\d{6}$","type":"string"}}}},{"if":{"properties":{"country":{"const":"SV","type":"string"}}},"then":{"properties":{"zip":{"pattern":"^1101$","type":"string"}}}},{"if":{"properties":{"country":{"const":"EG","type":"string"}}},"then":{"properties":{"zip":{"pattern":"^\\d{5}$","type":"string"}}}},{"if":{"properties":{"country":{"const":"EE","type":"string"}}},"then":{"properties":{"zip":{"pattern":"^\\d{5}$","type":"string"}}}},{"if":{"properties":{"country":{"const":"ET","type":"string"}}},"then":{"properties":{"zip":{"pattern":"^\\d{4}$","type":"string"}}}},{"if":{"properties":{"country":{"const":"FO","type":"string"}}},"then":{"properties":{"zip":{"pattern":"^\\d{3}$","type":"string"}}}},{"if":{"properties":{"country":{"const":"FI","type":"string"}}},"then":{"properties":{"zip":{"pattern":"^\\d{5}$","type":"string"}}}},{"if":{"properties":{"country":{"const":"FR","type":"string"}}},"then":{"properties":{"zip":{"pattern":"^\\d{5}$","type":"string"}}}},{"if":{"properties":{"country":{"const":"GF","type":"string"}}},"then":{"properties":{"zip":{"pattern":"^973\\d{2}$","type":"string"}}}},{"if":{"properties":{"country":{"const":"PF","type":"string"}}},"then":{"properties":{"zip":{"pattern":"^987\\d{2}$","type":"string"}}}},{"if":{"properties":{"country":{"const":"GE","type":"string"}}},"then":{"properties":{"zip":{"pattern":"^\\d{4}$","type":"string"}}}},{"if":{"properties":{"country":{"const":"DE","type":"string"}}},"then":{"properties":{"zip":{"pattern":"^\\d{5}$","type":"string"}}}},{"if":{"properties":{"country":{"const":"GI","type":"string"}}},"then":{"properties":{"zip":{"pattern":"^[Gg][Xx][1]{2} ?[1][Aa]{2}$","type":"string"}}}},{"if":{"properties":{"country":{"const":"GR","type":"string"}}},"then":{"properties":{"zip":{"pattern":"^\\d{3} ?\\d{2}$","type":"string"}}}},{"if":{"properties":{"country":{"const":"GL","type":"string"}}},"then":{"properties":{"zip":{"pattern":"^\\d{4}$","type":"string"}}}},{"if":{"properties":{"country":{"const":"GP","type":"string"}}},"then":{"properties":{"zip":{"pattern":"^971\\d{2}$","type":"string"}}}},{"if":{"properties":{"country":{"const":"GT","type":"string"}}},"then":{"properties":{"zip":{"pattern":"^\\d{5}$","type":"string"}}}},{"if":{"properties":{"country":{"const":"GG","type":"string"}}},"then":{"properties":{"zip":{"pattern":"^[A-Za-z]{2}\\d ?\\d[A-Za-z]{2}$","type":"string"}}}},{"if":{"properties":{"country":{"const":"GW","type":"string"}}},"then":{"properties":{"zip":{"pattern":"^\\d{4}$","type":"string"}}}},{"if":{"properties":{"country":{"const":"HT","type":"string"}}},"then":{"properties":{"zip":{"pattern":"^\\d{4}$","type":"string"}}}},{"if":{"properties":{"country":{"const":"HM","type":"string"}}},"then":{"properties":{"zip":{"pattern":"^\\d{4}$","type":"string"}}}},{"if":{"properties":{"country":{"const":"HN","type":"string"}}},"then":{"properties":{"zip":{"pattern":"^\\d{5}$","type":"string"}}}},{"if":{"properties":{"country":{"const":"HU","type":"string"}}},"then":{"properties":{"zip":{"pattern":"^\\d{4}$","type":"string"}}}},{"if":{"properties":{"country":{"const":"IS","type":"string"}}},"then":{"properties":{"zip":{"pattern":"^\\d{3}$","type":"string"}}}},{"if":{"properties":{"country":{"const":"IN","type":"string"}}},"then":{"properties":{"zip":{"pattern":"^\\d{6}$","type":"string"}}}},{"if":{"properties":{"country":{"const":"ID","type":"string"}}},"then":{"properties":{"zip":{"pattern":"^\\d{5}$","type":"string"}}}},{"if":{"properties":{"country":{"const":"IR","type":"string"}}},"then":{"properties":{"zip":{"pattern":"^\\d{5}(-?\\d{5})?$","type":"string"}}}},{"if":{"properties":{"country":{"const":"IQ","type":"string"}}},"then":{"properties":{"zip":{"pattern":"^\\d{5}$","type":"string"}}}},{"if":{"properties":{"country":{"const":"IM","type":"string"}}},"then":{"properties":{"zip":{"pattern":"^[Ii][Mm]\\d{1,2} \\d[A-Z]{2}$","type":"string"}}}},{"if":{"properties":{"country":{"const":"IL","type":"string"}}},"then":{"properties":{"zip":{"pattern":"^\\d{7}$","type":"string"}}}},{"if":{"properties":{"country":{"const":"IT","type":"string"}}},"then":{"properties":{"zip":{"pattern":"^\\d{5}$","type":"string"}}}},{"if":{"properties":{"country":{"const":"JP","type":"string"}}},"then":{"properties":{"zip":{"pattern":"^\\d{3}-\\d{4}$","type":"string"}}}},{"if":{"properties":{"country":{"const":"JE","type":"string"}}},"then":{"properties":{"zip":{"pattern":"^[Jj][Ee]\\d ?\\d[A-Za-z]{2}$","type":"string"}}}},{"if":{"properties":{"country":{"const":"JO","type":"string"}}},"then":{"properties":{"zip":{"pattern":"^\\d{5}$","type":"string"}}}},{"if":{"properties":{"country":{"const":"KZ","type":"string"}}},"then":{"properties":{"zip":{"pattern":"^\\d{6}$","type":"string"}}}},{"if":{"properties":{"country":{"const":"KE","type":"string"}}},"then":{"properties":{"zip":{"pattern":"^\\d{5}$","type":"string"}}}},{"if":{"properties":{"country":{"const":"XK","type":"string"}}},"then":{"properties":{"zip":{"pattern":"^\\d{5}$","type":"string"}}}},{"if":{"properties":{"country":{"const":"KW","type":"string"}}},"then":{"properties":{"zip":{"pattern":"^\\d{5}$","type":"string"}}}},{"if":{"properties":{"country":{"const":"KG","type":"string"}}},"then":{"properties":{"zip":{"pattern":"^\\d{6}$","type":"string"}}}},{"if":{"properties":{"country":{"const":"LV","type":"string"}}},"then":{"properties":{"zip":{"pattern":"^LV-\\d{4}$","type":"string"}}}},{"if":{"properties":{"country":{"const":"LA","type":"string"}}},"then":{"properties":{"zip":{"pattern":"^\\d{5}$","type":"string"}}}},{"if":{"properties":{"country":{"const":"LB","type":"string"}}},"then":{"properties":{"zip":{"pattern":"^\\d{4}( \\d{4})?$","type":"string"}}}},{"if":{"properties":{"country":{"const":"LS","type":"string"}}},"then":{"properties":{"zip":{"pattern":"^\\d{3}$","type":"string"}}}},{"if":{"properties":{"country":{"const":"LR","type":"string"}}},"then":{"properties":{"zip":{"pattern":"^\\d{4}$","type":"string"}}}},{"if":{"properties":{"country":{"const":"LY","type":"string"}}},"then":{"properties":{"zip":{"pattern":"^\\d{5}$","type":"string"}}}},{"if":{"properties":{"country":{"const":"LI","type":"string"}}},"then":{"properties":{"zip":{"pattern":"^\\d{4}$","type":"string"}}}},{"if":{"properties":{"country":{"const":"LT","type":"string"}}},"then":{"properties":{"zip":{"pattern":"^(LT-)?\\d{5}$","type":"string"}}}},{"if":{"properties":{"country":{"const":"LU","type":"string"}}},"then":{"properties":{"zip":{"pattern":"^\\d{4}$","type":"string"}}}},{"if":{"properties":{"country":{"const":"MK","type":"string"}}},"then":{"properties":{"zip":{"pattern":"^\\d{4}$","type":"string"}}}},{"if":{"properties":{"country":{"const":"MG","type":"string"}}},"then":{"properties":{"zip":{"pattern":"^\\d{3}$","type":"string"}}}},{"if":{"properties":{"country":{"const":"MV","type":"string"}}},"then":{"properties":{"zip":{"pattern":"^\\d{4,5}$","type":"string"}}}},{"if":{"properties":{"country":{"const":"MY","type":"string"}}},"then":{"properties":{"zip":{"pattern":"^\\d{5}$","type":"string"}}}},{"if":{"properties":{"country":{"const":"MT","type":"string"}}},"then":{"properties":{"zip":{"pattern":"^[A-Za-z]{3} ?\\d{4}$","type":"string"}}}},{"if":{"properties":{"country":{"const":"MQ","type":"string"}}},"then":{"properties":{"zip":{"pattern":"^972\\d{2}$","type":"string"}}}},{"if":{"properties":{"country":{"const":"YT","type":"string"}}},"then":{"properties":{"zip":{"pattern":"^976\\d{2}$","type":"string"}}}},{"if":{"properties":{"country":{"const":"MX","type":"string"}}},"then":{"properties":{"zip":{"pattern":"^\\d{5}$","type":"string"}}}},{"if":{"properties":{"country":{"const":"FM","type":"string"}}},"then":{"properties":{"zip":{"pattern":"^9694\\d$","type":"string"}}}},{"if":{"properties":{"country":{"const":"MD","type":"string"}}},"then":{"properties":{"zip":{"pattern":"^MD-\\d{4}$","type":"string"}}}},{"if":{"properties":{"country":{"const":"MC","type":"string"}}},"then":{"properties":{"zip":{"pattern":"^980\\d{2}$","type":"string"}}}},{"if":{"properties":{"country":{"const":"MN","type":"string"}}},"then":{"properties":{"zip":{"pattern":"^\\d{5}$","type":"string"}}}},{"if":{"properties":{"country":{"const":"ME","type":"string"}}},"then":{"properties":{"zip":{"pattern":"^\\d{5}$","type":"string"}}}},{"if":{"properties":{"country":{"const":"MS","type":"string"}}},"then":{"properties":{"zip":{"pattern":"^[Mm][Ss][Rr] ?\\d{4}$","type":"string"}}}},{"if":{"properties":{"country":{"const":"MA","type":"string"}}},"then":{"properties":{"zip":{"pattern":"^\\d{5}$","type":"string"}}}},{"if":{"properties":{"country":{"const":"MZ","type":"string"}}},"then":{"properties":{"zip":{"pattern":"^\\d{4}$","type":"string"}}}},{"if":{"properties":{"country":{"const":"MM","type":"string"}}},"then":{"properties":{"zip":{"pattern":"^\\d{5}$","type":"string"}}}},{"if":{"properties":{"country":{"const":"NA","type":"string"}}},"then":{"properties":{"zip":{"pattern":"^\\d{5}$","type":"string"}}}},{"if":{"properties":{"country":{"const":"NP","type":"string"}}},"then":{"properties":{"zip":{"pattern":"^\\d{5}$","type":"string"}}}},{"if":{"properties":{"country":{"const":"NL","type":"string"}}},"then":{"properties":{"zip":{"pattern":"^\\d{4} ?[A-Z]{2}$","type":"string"}}}},{"if":{"properties":{"country":{"const":"NC","type":"string"}}},"then":{"properties":{"zip":{"pattern":"^988\\d{2}$","type":"string"}}}},{"if":{"properties":{"country":{"const":"NZ","type":"string"}}},"then":{"properties":{"zip":{"pattern":"^\\d{4}$","type":"string"}}}},{"if":{"properties":{"country":{"const":"NI","type":"string"}}},"then":{"properties":{"zip":{"pattern":"^\\d{5}$","type":"string"}}}},{"if":{"properties":{"country":{"const":"NE","type":"string"}}},"then":{"properties":{"zip":{"pattern":"^\\d{4}$","type":"string"}}}},{"if":{"properties":{"country":{"const":"NG","type":"string"}}},"then":{"properties":{"zip":{"pattern":"^\\d{6}$","type":"string"}}}},{"if":{"properties":{"country":{"const":"NF","type":"string"}}},"then":{"properties":{"zip":{"pattern":"^\\d{4}$","type":"string"}}}},{"if":{"properties":{"country":{"const":"NO","type":"string"}}},"then":{"properties":{"zip":{"pattern":"^\\d{4}$","type":"string"}}}},{"if":{"properties":{"country":{"const":"OM","type":"string"}}},"then":{"properties":{"zip":{"pattern":"^\\d{3}$","type":"string"}}}},{"if":{"properties":{"country":{"const":"PK","type":"string"}}},"then":{"properties":{"zip":{"pattern":"^\\d{5}$","type":"string"}}}},{"if":{"properties":{"country":{"const":"PA","type":"string"}}},"then":{"properties":{"zip":{"pattern":"^(0\\d|10)\\d{2}$","type":"string"}}}},{"if":{"properties":{"country":{"const":"PG","type":"string"}}},"then":{"properties":{"zip":{"pattern":"^\\d{3}$","type":"string"}}}},{"if":{"properties":{"country":{"const":"PY","type":"string"}}},"then":{"properties":{"zip":{"pattern":"^\\d{4}$","type":"string"}}}},{"if":{"properties":{"country":{"const":"PE","type":"string"}}},"then":{"properties":{"zip":{"pattern":"^\\d{5}$","type":"string"}}}},{"if":{"properties":{"country":{"const":"PH","type":"string"}}},"then":{"properties":{"zip":{"pattern":"^\\d{4}$","type":"string"}}}},{"if":{"properties":{"country":{"const":"PL","type":"string"}}},"then":{"properties":{"zip":{"pattern":"^\\d{2}[- ]?\\d{3}$","type":"string"}}}},{"if":{"properties":{"country":{"const":"PT","type":"string"}}},"then":{"properties":{"zip":{"pattern":"^\\d{4}[- ]?\\d{3}$","type":"string"}}}},{"if":{"properties":{"country":{"const":"RE","type":"string"}}},"then":{"properties":{"zip":{"pattern":"^974\\d{2}$","type":"string"}}}},{"if":{"properties":{"country":{"const":"RO","type":"string"}}},"then":{"properties":{"zip":{"pattern":"^\\d{6}$","type":"string"}}}},{"if":{"properties":{"country":{"const":"RU","type":"string"}}},"then":{"properties":{"zip":{"pattern":"^\\d{6}$","type":"string"}}}},{"if":{"properties":{"country":{"const":"BL","type":"string"}}},"then":{"properties":{"zip":{"pattern":"^97133$","type":"string"}}}},{"if":{"properties":{"country":{"const":"MF","type":"string"}}},"then":{"properties":{"zip":{"pattern":"^97150$","type":"string"}}}},{"if":{"properties":{"country":{"const":"PM","type":"string"}}},"then":{"properties":{"zip":{"pattern":"^97500$","type":"string"}}}},{"if":{"properties":{"country":{"const":"VC","type":"string"}}},"then":{"properties":{"zip":{"pattern":"^[Vv][Cc]\\d{4}$","type":"string"}}}},{"if":{"properties":{"country":{"const":"SM","type":"string"}}},"then":{"properties":{"zip":{"pattern":"^4789\\d$","type":"string"}}}},{"if":{"properties":{"country":{"const":"SA","type":"string"}}},"then":{"properties":{"zip":{"pattern":"^\\d{5}(-\\d{4})?$","type":"string"}}}},{"if":{"properties":{"country":{"const":"SN","type":"string"}}},"then":{"properties":{"zip":{"pattern":"^\\d{5}$","type":"string"}}}},{"if":{"properties":{"country":{"const":"RS","type":"string"}}},"then":{"properties":{"zip":{"pattern":"^\\d{5}$","type":"string"}}}},{"if":{"properties":{"country":{"const":"SG","type":"string"}}},"then":{"properties":{"zip":{"pattern":"^\\d{6}$","type":"string"}}}},{"if":{"properties":{"country":{"const":"SK","type":"string"}}},"then":{"properties":{"zip":{"pattern":"^\\d{3} \\d{2}$","type":"string"}}}},{"if":{"properties":{"country":{"const":"SI","type":"string"}}},"then":{"properties":{"zip":{"pattern":"^(SI-?)?\\d{4}$","type":"string"}}}},{"if":{"properties":{"country":{"const":"ZA","type":"string"}}},"then":{"properties":{"zip":{"pattern":"^\\d{4}$","type":"string"}}}},{"if":{"properties":{"country":{"const":"KR","type":"string"}}},"then":{"properties":{"zip":{"pattern":"^\\d{5}$","type":"string"}}}},{"if":{"properties":{"country":{"const":"ES","type":"string"}}},"then":{"properties":{"zip":{"pattern":"^\\d{5}$","type":"string"}}}},{"if":{"properties":{"country":{"const":"LK","type":"string"}}},"then":{"properties":{"zip":{"pattern":"^\\d{5}$","type":"string"}}}},{"if":{"properties":{"country":{"const":"SD","type":"string"}}},"then":{"properties":{"zip":{"pattern":"^\\d{5}$","type":"string"}}}},{"if":{"properties":{"country":{"const":"SZ","type":"string"}}},"then":{"properties":{"zip":{"pattern":"^[A-Za-z]\\d{3}$","type":"string"}}}},{"if":{"properties":{"country":{"const":"SE","type":"string"}}},"then":{"properties":{"zip":{"pattern":"^(se-|SE-)?\\d{3} ?\\d{2}$","type":"string"}}}},{"if":{"properties":{"country":{"const":"CH","type":"string"}}},"then":{"properties":{"zip":{"pattern":"^\\d{4}$","type":"string"}}}},{"if":{"properties":{"country":{"const":"SJ","type":"string"}}},"then":{"properties":{"zip":{"pattern":"^\\d{4}$","type":"string"}}}},{"if":{"properties":{"country":{"const":"TW","type":"string"}}},"then":{"properties":{"zip":{"pattern":"^\\d{5}$","type":"string"}}}},{"if":{"properties":{"country":{"const":"TJ","type":"string"}}},"then":{"properties":{"zip":{"pattern":"^\\d{6}$","type":"string"}}}},{"if":{"properties":{"country":{"const":"TH","type":"string"}}},"then":{"properties":{"zip":{"pattern":"^\\d{5}$","type":"string"}}}},{"if":{"properties":{"country":{"const":"TT","type":"string"}}},"then":{"properties":{"zip":{"pattern":"^\\d{6}$","type":"string"}}}},{"if":{"properties":{"country":{"const":"TN","type":"string"}}},"then":{"properties":{"zip":{"pattern":"^\\d{4}$","type":"string"}}}},{"if":{"properties":{"country":{"const":"TR","type":"string"}}},"then":{"properties":{"zip":{"pattern":"^\\d{5}$","type":"string"}}}},{"if":{"properties":{"country":{"const":"TM","type":"string"}}},"then":{"properties":{"zip":{"pattern":"^\\d{6}$","type":"string"}}}},{"if":{"properties":{"country":{"const":"UA","type":"string"}}},"then":{"properties":{"zip":{"pattern":"^\\d{5}$","type":"string"}}}},{"if":{"properties":{"country":{"const":"GB","type":"string"}}},"then":{"properties":{"zip":{"pattern":"^[A-Za-z][A-Ha-hK-Yk-y]?\\d[A-Za-z0-9]? ?\\d[A-Za-z]{2}$","type":"string"}}}},{"if":{"properties":{"country":{"const":"US","type":"string"}}},"then":{"properties":{"zip":{"pattern":"^\\d{5}([- ]\\d{4})?$","type":"string"}}}},{"if":{"properties":{"country":{"const":"UY","type":"string"}}},"then":{"properties":{"zip":{"pattern":"^\\d{5}$","type":"string"}}}},{"if":{"properties":{"country":{"const":"UZ","type":"string"}}},"then":{"properties":{"zip":{"pattern":"^\\d{3} \\d{3}$","type":"string"}}}},{"if":{"properties":{"country":{"const":"VA","type":"string"}}},"then":{"properties":{"zip":{"pattern":"^120$","type":"string"}}}},{"if":{"properties":{"country":{"const":"VE","type":"string"}}},"then":{"properties":{"zip":{"pattern":"^\\d{4}( [a-zA-Z])?$","type":"string"}}}},{"if":{"properties":{"country":{"const":"VN","type":"string"}}},"then":{"properties":{"zip":{"pattern":"^\\d{6}$","type":"string"}}}},{"if":{"properties":{"country":{"const":"WF","type":"string"}}},"then":{"properties":{"zip":{"pattern":"^986\\d{2}$","type":"string"}}}},{"if":{"properties":{"country":{"const":"ZM","type":"string"}}},"then":{"properties":{"zip":{"pattern":"^\\d{5}$","type":"string"}}}},{"if":{"properties":{"country":{"const":"AS","type":"string"}}},"then":{"properties":{"zip":{"pattern":"^96799$","type":"string"}}}},{"if":{"properties":{"country":{"const":"GU","type":"string"}}},"then":{"properties":{"zip":{"pattern":"^969\\d{2}$","type":"string"}}}},{"if":{"properties":{"country":{"const":"MH","type":"string"}}},"then":{"properties":{"zip":{"pattern":"^969\\d{2}$","type":"string"}}}},{"if":{"properties":{"country":{"const":"MP","type":"string"}}},"then":{"properties":{"zip":{"pattern":"^969\\d{2}$","type":"string"}}}},{"if":{"properties":{"country":{"const":"PW","type":"string"}}},"then":{"properties":{"zip":{"pattern":"^96940$","type":"string"}}}},{"if":{"properties":{"country":{"const":"PR","type":"string"}}},"then":{"properties":{"zip":{"pattern":"^00[679]\\d{2}$","type":"string"}}}},{"if":{"properties":{"country":{"const":"VI","type":"string"}}},"then":{"properties":{"zip":{"pattern":"^008\\d{2}$","type":"string"}}}},{"if":{"properties":{"country":{"const":"AC","type":"string"}}},"then":{"properties":{"zip":{"pattern":"^ASCN 1ZZ$","type":"string"}}}},{"if":{"properties":{"country":{"const":"IO","type":"string"}}},"then":{"properties":{"zip":{"pattern":"^BBND 1ZZ$","type":"string"}}}},{"if":{"properties":{"country":{"const":"FK","type":"string"}}},"then":{"properties":{"zip":{"pattern":"^FIQQ 1ZZ$","type":"string"}}}},{"if":{"properties":{"country":{"const":"PN","type":"string"}}},"then":{"properties":{"zip":{"pattern":"^PCRN 1ZZ$","type":"string"}}}},{"if":{"properties":{"country":{"const":"GS","type":"string"}}},"then":{"properties":{"zip":{"pattern":"^SIQQ 1ZZ$","type":"string"}}}},{"if":{"properties":{"country":{"const":"SH","type":"string"}}},"then":{"properties":{"zip":{"pattern":"^(TDCU|ASCN|STHL) ?1(ZZ|zz)$","type":"string"}}}},{"if":{"properties":{"country":{"const":"TC","type":"string"}}},"then":{"properties":{"zip":{"pattern":"^TKCA 1ZZ$","type":"string"}}}}],"type":"object"}},"$id":"file://schemas/world-postcodes.json","type":"object"}
